spotizerr_auth/__init__.py
spotizerr_auth/main.py
spotizerr_auth_phoenix-0.0.16.dist-info/METADATA
spotizerr_auth_phoenix-0.0.16.dist-info/WHEEL
spotizerr_auth_phoenix-0.0.16.dist-info/entry_points.txt
spotizerr_auth_phoenix-0.0.16.dist-info/top_level.txt
spotizerr_auth_phoenix-0.0.16.dist-info/RECORD
