Metadata-Version: 2.4
Name: spotizerr-auth-phoenix
Version: 0.0.16
Summary: A Spotizerr authentication utility for configuring Spotify credentials
Home-page: https://lavaforge.org/spotizerrphoenix/spotizerr-auth-phoenix
Author: spotizerr-phoenix
License: GPL-3.0-or-later
Classifier: Programming Language :: Python :: 3
Classifier: License :: OSI Approved :: GNU General Public License v3 or later (GPLv3+)
Classifier: Operating System :: OS Independent
Requires-Python: >=3.7
Requires-Dist: librespot-spotizerr-phoenix
Requires-Dist: requests
Requires-Dist: rich
